b2btest/__init__.py
b2btest/b2btest.py
b2btest/b2btest_test.py
b2btest/difftext.py
b2btest/diffxml.py
b2btest/entrypoints.py
b2btest-1.4.2.data/scripts/back2back
b2btest-1.4.2.dist-info/METADATA
b2btest-1.4.2.dist-info/WHEEL
b2btest-1.4.2.dist-info/entry_points.txt
b2btest-1.4.2.dist-info/top_level.txt
b2btest-1.4.2.dist-info/RECORD
