Metadata-Version: 2.1
Name: b2btest
Version: 1.4.2
Summary: Light framework to setup back-to-back test
Home-page: https://github.com/vokimon/back2back
Author: David Garcia Garzon
Author-email: voki@canvoki.net
License: GNU General Public License v3 or later (GPLv3+)
Classifier: Programming Language :: Python
Classifier: Programming Language :: Python :: 2
Classifier: Programming Language :: Python :: 3
Classifier: Topic :: Software Development :: Libraries :: Python Modules
Classifier: Intended Audience :: Developers
Classifier: Development Status :: 5 - Production/Stable
Classifier: License :: OSI Approved :: GNU General Public License v3 or later (GPLv3+)
Classifier: Operating System :: OS Independent
Requires-Dist: consolemsg
Requires-Dist: yamlns
Requires-Dist: pathlib2; python_version < "3.5"
Requires-Dist: setuptools>40.5
Requires-Dist: lxml
